trustpoint_devid_module/__init__.py
trustpoint_devid_module/__main__.py
trustpoint_devid_module/cli.py
trustpoint_devid_module/decorator.py
trustpoint_devid_module/exceptions.py
trustpoint_devid_module/schema.py
trustpoint_devid_module/serializer/__init__.py
trustpoint_devid_module/serializer/base.py
trustpoint_devid_module/serializer/certificate.py
trustpoint_devid_module/serializer/credential.py
trustpoint_devid_module/serializer/key.py
trustpoint_devid_module/service_interface.py
trustpoint_devid_module/validator.py
trustpoint_devid_module-0.2.3.dist-info/LICENSE
trustpoint_devid_module-0.2.3.dist-info/METADATA
trustpoint_devid_module-0.2.3.dist-info/WHEEL
trustpoint_devid_module-0.2.3.dist-info/entry_points.txt
trustpoint_devid_module-0.2.3.dist-info/RECORD
