Metadata-Version: 2.3
Name: trustpoint-devid-module
Version: 0.2.3
Summary: 
Author: TrustPoint-Project
Requires-Python: >=3.10,<4.0
Classifier: Programming Language :: Python :: 3
Classifier: Programming Language :: Python :: 3.10
Classifier: Programming Language :: Python :: 3.11
Classifier: Programming Language :: Python :: 3.12
Classifier: Programming Language :: Python :: 3.13
Requires-Dist: click (>=8.1.8,<9.0.0)
Requires-Dist: cryptography (>=44.0.0,<45.0.0)
Requires-Dist: platformdirs (>=4.3.6,<5.0.0)
Requires-Dist: prettytable (>=3.13.0,<4.0.0)
Requires-Dist: pyasn1 (>=0.6.1,<0.7.0)
Requires-Dist: pyasn1-modules (>=0.4.1,<0.5.0)
Requires-Dist: pydantic (>=2.10.6,<3.0.0)
